langchain_markitdown/__init__.py
langchain_markitdown/base_loader.py
langchain_markitdown/utils.py
langchain_markitdown/loaders/__init__.py
langchain_markitdown/loaders/audio_loader.py
langchain_markitdown/loaders/bing_serp_loader.py
langchain_markitdown/loaders/doc_intel_loader.py
langchain_markitdown/loaders/docx_loader.py
langchain_markitdown/loaders/epub_loader.py
langchain_markitdown/loaders/html_loader.py
langchain_markitdown/loaders/image_loader.py
langchain_markitdown/loaders/ipynb_loader.py
langchain_markitdown/loaders/outlook_msg_loader.py
langchain_markitdown/loaders/pdf_loader.py
langchain_markitdown/loaders/plain_text_loader.py
langchain_markitdown/loaders/pptx_loader.py
langchain_markitdown/loaders/rss_loader.py
langchain_markitdown/loaders/rtf_loader.py
langchain_markitdown/loaders/wikipedia_loader.py
langchain_markitdown/loaders/xlsx_loader.py
langchain_markitdown/loaders/youtube_loader.py
langchain_markitdown/loaders/zip_loader.py
langchain_markitdown-1.0.0.dist-info/licenses/LICENSE
langchain_markitdown-1.0.0.dist-info/METADATA
langchain_markitdown-1.0.0.dist-info/WHEEL
langchain_markitdown-1.0.0.dist-info/top_level.txt
langchain_markitdown-1.0.0.dist-info/RECORD
