Metadata-Version: 2.4
Name: langchain-markitdown
Version: 1.0.0
Summary: LangChain data loaders based on Markdown by @untrueaxioms.
Home-page: https://github.com/nsasto/langchain-markitdown
Author: Nathan Sasto
License: MIT
Classifier: Development Status :: 3 - Alpha
Classifier: Intended Audience :: Developers
Classifier: Topic :: Software Development :: Libraries :: Python Modules
Classifier: Topic :: Text Processing :: Markup :: Markdown
Classifier: Programming Language :: Python :: 3
Classifier: Programming Language :: Python :: 3.8
Classifier: Programming Language :: Python :: 3.9
Classifier: Programming Language :: Python :: 3.10
Classifier: Programming Language :: Python :: 3.11
Classifier: Programming Language :: Python :: 3.12
Classifier: License :: OSI Approved :: MIT License
Classifier: Operating System :: OS Independent
Requires-Python: >=3.8
License-File: LICENSE
Requires-Dist: markitdown[all]>=0.1.3
Requires-Dist: langchain-core>=1.0.4
Requires-Dist: langchain-text-splitters>=1.0.0
Requires-Dist: langchain-openai>=1.0.2
Requires-Dist: python-docx>=1.2.0
Requires-Dist: pillow>=12.0.0
Provides-Extra: dev
Requires-Dist: pytest; extra == "dev"
Requires-Dist: python-docx; extra == "dev"
Requires-Dist: python-pptx; extra == "dev"
Requires-Dist: openpyxl; extra == "dev"
Requires-Dist: pytest-cov; extra == "dev"
Dynamic: author
Dynamic: classifier
Dynamic: description
Dynamic: description-content-type
Dynamic: home-page
Dynamic: license
Dynamic: license-file
Dynamic: provides-extra
Dynamic: requires-dist
Dynamic: requires-python
Dynamic: summary
